{"metadata": {"dbt_schema_version": "https://schemas.getdbt.com/dbt/run-results/v3.json", "dbt_version": "0.21.1", "generated_at": "2022-02-17T06:21:58.400304Z", "invocation_id": "6b217057-96e0-4458-82cb-1ae4d02e415f", "env": {}}, "results": [{"status": "success", "timing": [{"name": "compile", "started_at": "2022-02-17T06:21:52.227692Z", "completed_at": "2022-02-17T06:21:52.256938Z"}, {"name": "execute", "started_at": "2022-02-17T06:21:52.257070Z", "completed_at": "2022-02-17T06:21:53.112778Z"}], "thread_id": "Thread-2", "execution_time": 0.8856699466705322, "adapter_response": {"_message": "OK", "code": "CREATE VIEW"}, "message": "OK", "failures": null, "unique_id": "model.jaffle_shop.stg_customers"}, {"status": "success", "timing": [{"name": "compile", "started_at": "2022-02-17T06:21:52.236123Z", "completed_at": "2022-02-17T06:21:52.267185Z"}, {"name": "execute", "started_at": "2022-02-17T06:21:52.267338Z", "completed_at": "2022-02-17T06:21:53.152722Z"}], "thread_id": "Thread-4", "execution_time": 0.9171099662780762, "adapter_response": {"_message": "OK", "code": "CREATE VIEW"}, "message": "OK", "failures": null, "unique_id": "model.jaffle_shop.stg_payments"}, {"status": "success", "timing": [{"name": "compile", "started_at": "2022-02-17T06:21:52.232974Z", "completed_at": "2022-02-17T06:21:52.251579Z"}, {"name": "execute", "started_at": "2022-02-17T06:21:52.251724Z", "completed_at": "2022-02-17T06:21:53.191495Z"}], "thread_id": "Thread-3", "execution_time": 0.958998441696167, "adapter_response": {"_message": "OK", "code": "CREATE VIEW"}, "message": "OK", "failures": null, "unique_id": "model.jaffle_shop.stg_orders"}, {"status": "success", "timing": [{"name": "compile", "started_at": "2022-02-17T06:21:53.154536Z", "completed_at": "2022-02-17T06:21:53.172525Z"}, {"name": "execute", "started_at": "2022-02-17T06:21:53.172669Z", "completed_at": "2022-02-17T06:21:54.053578Z"}], "thread_id": "Thread-2", "execution_time": 0.8996517658233643, "adapter_response": {"_message": "OK", "code": "CREATE VIEW"}, "message": "OK", "failures": null, "unique_id": "model.jaffle_shop.int_orders_pivoted"}, {"status": "success", "timing": [{"name": "compile", "started_at": "2022-02-17T06:21:53.193433Z", "completed_at": "2022-02-17T06:21:53.224097Z"}, {"name": "execute", "started_at": "2022-02-17T06:21:53.224258Z", "completed_at": "2022-02-17T06:21:55.691327Z"}], "thread_id": "Thread-4", "execution_time": 2.4985713958740234, "adapter_response": {"_message": "CREATE TABLE (99.0 rows, 5.2 KB processed)", "code": "CREATE TABLE", "rows_affected": 99, "bytes_processed": 5355}, "message": "CREATE TABLE (99.0 rows, 5.2 KB processed)", "failures": null, "unique_id": "model.jaffle_shop.fct_orders"}, {"status": "success", "timing": [{"name": "compile", "started_at": "2022-02-17T06:21:52.222662Z", "completed_at": "2022-02-17T06:21:53.203934Z"}, {"name": "execute", "started_at": "2022-02-17T06:21:53.204087Z", "completed_at": "2022-02-17T06:21:55.825905Z"}], "thread_id": "Thread-1", "execution_time": 3.6038641929626465, "adapter_response": {"_message": "CREATE TABLE (366.0 rows, 0.0 Bytes processed)", "code": "CREATE TABLE", "rows_affected": 366, "bytes_processed": 0}, "message": "CREATE TABLE (366.0 rows, 0.0 Bytes processed)", "failures": null, "unique_id": "model.jaffle_shop.all_dates"}, {"status": "success", "timing": [{"name": "compile", "started_at": "2022-02-17T06:21:55.693472Z", "completed_at": "2022-02-17T06:21:55.710385Z"}, {"name": "execute", "started_at": "2022-02-17T06:21:55.710539Z", "completed_at": "2022-02-17T06:21:58.397363Z"}], "thread_id": "Thread-3", "execution_time": 2.7045235633850098, "adapter_response": {"_message": "CREATE TABLE (100.0 rows, 5.0 KB processed)", "code": "CREATE TABLE", "rows_affected": 100, "bytes_processed": 5154}, "message": "CREATE TABLE (100.0 rows, 5.0 KB processed)", "failures": null, "unique_id": "model.jaffle_shop.dim_customers"}], "elapsed_time": 6.638633966445923, "args": {"log_format": "default", "write_json": true, "use_experimental_parser": false, "profiles_dir": "/home/restricted/.dbt", "vars": "{}\n", "use_cache": true, "version_check": true, "which": "run", "rpc_method": "run"}}